README.md
setup.py
asgard_api_plugin_metrics_mesos.egg-info/PKG-INFO
asgard_api_plugin_metrics_mesos.egg-info/SOURCES.txt
asgard_api_plugin_metrics_mesos.egg-info/dependency_links.txt
asgard_api_plugin_metrics_mesos.egg-info/entry_points.txt
asgard_api_plugin_metrics_mesos.egg-info/requires.txt
asgard_api_plugin_metrics_mesos.egg-info/top_level.txt
metrics/__init__.py
metrics/config.py
metrics/mesos.py
metrics/util.py