Metadata-Version: 1.1
Name: asgard-api-plugin-metrics-mesos
Version: 0.9.0rc1
Summary: Asgard API endpoints to get Apache Mesos metrics
Home-page: https://github.com/B2W-BIT/asgard-api-plugin-metrics-mesos
Author: Dalton Barreto
Author-email: daltonmatos@gmail.com
License: MIT
Platform: UNKNOWN
Classifier: Programming Language :: Python :: 3.6
